aircraft_design/__init__.py
aircraft_design/basic_airfoils/E423.dat
aircraft_design/basic_airfoils/NACA0012.dat
aircraft_design/basic_airfoils/S1223.dat
aircraft_design/basic_airfoils/SD7032-NEG.dat
aircraft_design/bin/.foo
aircraft_design/classes/__init__.py
aircraft_design/classes/aircraft.py
aircraft_design/classes/airfoil.py
aircraft_design/classes/errors.py
aircraft_design/classes/runner.py
aircraft_design/classes/wing.py
aircraft_design/classes/xfoil_controler.py
aircraft_design-0.0.17.dist-info/LICENSE
aircraft_design-0.0.17.dist-info/METADATA
aircraft_design-0.0.17.dist-info/WHEEL
aircraft_design-0.0.17.dist-info/RECORD
