Metadata-Version: 2.1
Name: aircraft-design
Version: 0.0.17
Summary: Condensed module for Aircraft Design
Home-page: https://pypi.org/project/aircraft-design/
License: MIT
Keywords: aircraft,design,VLM,vortex lattice
Author: Nisus Aerodesign
Author-email: ufsc.nisus@gmail.com
Maintainer: Irisson Lima
Maintainer-email: irisson2203@gmail.com
Requires-Python: >=3.9,<3.12
Classifier: License :: OSI Approved :: MIT License
Classifier: Programming Language :: Python :: 3
Classifier: Programming Language :: Python :: 3.9
Classifier: Programming Language :: Python :: 3.10
Classifier: Programming Language :: Python :: 3.11
Requires-Dist: avlwrapper (>=0.3.4,<0.4.0)
Requires-Dist: matplotlib (>=3.6.3,<4.0.0)
Requires-Dist: numpy (>=1.24.2,<2.0.0)
Requires-Dist: pandas (>=2.0.0,<3.0.0)
Requires-Dist: requests (>=2.28.2,<3.0.0)
Requires-Dist: scipy (>=1.10.0,<2.0.0)
Project-URL: Repository, https://github.com/NisusAerodesign/aircraft-design
